in method:advanceToIntersection, at line:159, inst:invokespecial < Application, Lorg/apache/accumulo/core/iterators/user/IntersectingIterator, advanceToIntersection()V > 1 @1 exception:3
in method:advanceToIntersection, at line:159, inst:4 = getfield < Application, Lorg/apache/accumulo/core/iterators/user/IndexedDocIterator, topKey, <Application,Lorg/apache/accumulo/core/data/Key> > 1
in method:advanceToIntersection, at line:160, inst:conditional branch(ne, to iindex=7) 4,5
in method:advanceToIntersection, at line:160, inst:6 = getstatic < Application, Lorg/apache/accumulo/core/iterators/user/IndexedDocIterator, log, <Application,Lorg/slf4j/Logger> >
in method:advanceToIntersection, at line:160, inst:8 = invokeinterface < Application, Lorg/slf4j/Logger, isTraceEnabled()Z > 6 @15 exception:7
in method:advanceToIntersection, at line:160, inst:conditional branch(eq, to iindex=23) 8,9
in method:advanceToIntersection, at line:161, inst:10 = getstatic < Application, Lorg/apache/accumulo/core/iterators/user/IndexedDocIterator, log, <Application,Lorg/slf4j/Logger> >
in method:advanceToIntersection, at line:162, inst:11 = new <Application,Ljava/lang/StringBuilder>@26
in method:advanceToIntersection, at line:162, inst:invokespecial < Application, Ljava/lang/StringBuilder, <init>()V > 11 @30 exception:12
in method:advanceToIntersection, at line:162, inst:15 = invokevirtual < Application, Ljava/lang/StringBuilder, append(Ljava/lang/String;)Ljava/lang/StringBuilder; > 11,13 @35 exception:14
in method:advanceToIntersection, at line:162, inst:16 = getfield < Application, Lorg/apache/accumulo/core/iterators/user/IndexedDocIterator, topKey, <Application,Lorg/apache/accumulo/core/data/Key> > 1
in method:advanceToIntersection, at line:162, inst:18 = invokevirtual < Application, Lorg/apache/accumulo/core/data/Key, toString()Ljava/lang/String; > 16 @42 exception:17
in method:advanceToIntersection, at line:162, inst:20 = invokevirtual < Application, Ljava/lang/StringBuilder, append(Ljava/lang/String;)Ljava/lang/StringBuilder; > 15,18 @45 exception:19
in method:advanceToIntersection, at line:162, inst:22 = invokevirtual < Application, Ljava/lang/StringBuilder, toString()Ljava/lang/String; > 20 @48 exception:21
in method:advanceToIntersection, at line:162, inst:invokeinterface < Application, Lorg/slf4j/Logger, trace(Ljava/lang/String;)V > 10,22 @51 exception:23
in method:advanceToIntersection, at line:163, inst:25 = invokevirtual < Application, Lorg/apache/accumulo/core/iterators/user/IndexedDocIterator, buildDocKey()Lorg/apache/accumulo/core/data/Key; > 1 @57 exception:24
in method:advanceToIntersection, at line:163, inst:26 = getfield < Application, Lorg/apache/accumulo/core/iterators/user/IndexedDocIterator, docSource, <Application,Lorg/apache/accumulo/core/iterators/SortedKeyValueIterator> > 1
in method:advanceToIntersection, at line:163, inst:27 = new <Application,Lorg/apache/accumulo/core/data/Range>@65
in method:advanceToIntersection, at line:163, inst:invokespecial < Application, Lorg/apache/accumulo/core/data/Range, <init>(Lorg/apache/accumulo/core/data/Key;ZLorg/apache/accumulo/core/data/Key;Z)V > 27,25,28,5,9 @73 exception:29
in method:advanceToIntersection, at line:163, inst:30 = getfield < Application, Lorg/apache/accumulo/core/iterators/user/IndexedDocIterator, docColfSet, <Application,Ljava/util/Set> > 1
in method:advanceToIntersection, at line:163, inst:invokeinterface < Application, Lorg/apache/accumulo/core/iterators/SortedKeyValueIterator, seek(Lorg/apache/accumulo/core/data/Range;Ljava/util/Collection;Z)V > 26,27,30,28 @81 exception:31
in method:advanceToIntersection, at line:163, inst:32 = getstatic < Application, Lorg/apache/accumulo/core/iterators/user/IndexedDocIterator, log, <Application,Lorg/slf4j/Logger> >
in method:advanceToIntersection, at line:163, inst:33 = new <Application,Ljava/lang/StringBuilder>@89
in method:advanceToIntersection, at line:163, inst:invokespecial < Application, Ljava/lang/StringBuilder, <init>()V > 33 @93 exception:34
in method:advanceToIntersection, at line:163, inst:37 = invokevirtual < Application, Ljava/lang/StringBuilder, append(Ljava/lang/String;)Ljava/lang/StringBuilder; > 33,35 @98 exception:36
in method:advanceToIntersection, at line:163, inst:38 = getfield < Application, Lorg/apache/accumulo/core/iterators/user/IndexedDocIterator, docSource, <Application,Lorg/apache/accumulo/core/iterators/SortedKeyValueIterator> > 1
in method:advanceToIntersection, at line:163, inst:40 = invokeinterface < Application, Lorg/apache/accumulo/core/iterators/SortedKeyValueIterator, getTopKey()Lorg/apache/hadoop/io/WritableComparable; > 38 @105 exception:39
in method:advanceToIntersection, at line:163, inst:41 = checkcast <Application,Lorg/apache/accumulo/core/data/Key>40 <Application,Lorg/apache/accumulo/core/data/Key>
in method:advanceToIntersection, at line:163, inst:43 = invokevirtual < Application, Lorg/apache/accumulo/core/data/Key, toString()Ljava/lang/String; > 41 @113 exception:42
in method:advanceToIntersection, at line:163, inst:45 = invokevirtual < Application, Ljava/lang/StringBuilder, append(Ljava/lang/String;)Ljava/lang/StringBuilder; > 37,43 @116 exception:44
in method:advanceToIntersection, at line:163, inst:47 = invokevirtual < Application, Ljava/lang/StringBuilder, toString()Ljava/lang/String; > 45 @119 exception:46
in method:advanceToIntersection, at line:163, inst:invokeinterface < Application, Lorg/slf4j/Logger, debug(Ljava/lang/String;)V > 32,47 @122 exception:48
in method:advanceToIntersection, at line:163, inst:49 = getfield < Application, Lorg/apache/accumulo/core/iterators/user/IndexedDocIterator, docSource, <Application,Lorg/apache/accumulo/core/iterators/SortedKeyValueIterator> > 1
in method:advanceToIntersection, at line:163, inst:51 = invokeinterface < Application, Lorg/apache/accumulo/core/iterators/SortedKeyValueIterator, hasTop()Z > 49 @131 exception:50
in method:advanceToIntersection, at line:164, inst:conditional branch(eq, to iindex=73) 51,9
in method:advanceToIntersection, at line:164, inst:52 = getfield < Application, Lorg/apache/accumulo/core/iterators/user/IndexedDocIterator, docSource, <Application,Lorg/apache/accumulo/core/iterators/SortedKeyValueIterator> > 1
in method:advanceToIntersection, at line:165, inst:54 = invokeinterface < Application, Lorg/apache/accumulo/core/iterators/SortedKeyValueIterator, getTopKey()Lorg/apache/hadoop/io/WritableComparable; > 52 @144 exception:53
in method:advanceToIntersection, at line:165, inst:55 = checkcast <Application,Lorg/apache/accumulo/core/data/Key>54 <Application,Lorg/apache/accumulo/core/data/Key>
in method:advanceToIntersection, at line:165, inst:56 = getstatic < Application, Lorg/apache/accumulo/core/data/PartialKey, ROW_COLFAM_COLQUAL, <Application,Lorg/apache/accumulo/core/data/PartialKey> >
in method:advanceToIntersection, at line:165, inst:58 = invokevirtual < Application, Lorg/apache/accumulo/core/data/Key, equals(Lorg/apache/accumulo/core/data/Key;Lorg/apache/accumulo/core/data/PartialKey;)Z > 25,55,56 @155 exception:57
in method:advanceToIntersection, at line:165, inst:conditional branch(eq, to iindex=73) 58,9
in method:advanceToIntersection, at line:165, inst:59 = getfield < Application, Lorg/apache/accumulo/core/iterators/user/IndexedDocIterator, docSource, <Application,Lorg/apache/accumulo/core/iterators/SortedKeyValueIterator> > 1
in method:advanceToIntersection, at line:165, inst:61 = invokeinterface < Application, Lorg/apache/accumulo/core/iterators/SortedKeyValueIterator, getTopValue()Lorg/apache/hadoop/io/Writable; > 59 @166 exception:60
in method:advanceToIntersection, at line:165, inst:62 = checkcast <Application,Lorg/apache/accumulo/core/data/Value>61 <Application,Lorg/apache/accumulo/core/data/Value>
in method:advanceToIntersection, at line:165, inst:putfield 1.< Application, Lorg/apache/accumulo/core/iterators/user/IndexedDocIterator, value, <Application,Lorg/apache/accumulo/core/data/Value> > = 62
in method:advanceToIntersection, at line:165, inst:63 = getstatic < Application, Lorg/apache/accumulo/core/iterators/user/IndexedDocIterator, log, <Application,Lorg/slf4j/Logger> >
in method:advanceToIntersection, at line:165, inst:64 = new <Application,Ljava/lang/StringBuilder>@180
in method:advanceToIntersection, at line:165, inst:invokespecial < Application, Ljava/lang/StringBuilder, <init>()V > 64 @184 exception:65
in method:advanceToIntersection, at line:165, inst:68 = invokevirtual < Application, Ljava/lang/StringBuilder, append(Ljava/lang/String;)Ljava/lang/StringBuilder; > 64,66 @189 exception:67
in method:advanceToIntersection, at line:165, inst:69 = getfield < Application, Lorg/apache/accumulo/core/iterators/user/IndexedDocIterator, value, <Application,Lorg/apache/accumulo/core/data/Value> > 1
in method:advanceToIntersection, at line:165, inst:71 = invokevirtual < Application, Lorg/apache/accumulo/core/data/Value, toString()Ljava/lang/String; > 69 @196 exception:70
in method:advanceToIntersection, at line:165, inst:73 = invokevirtual < Application, Ljava/lang/StringBuilder, append(Ljava/lang/String;)Ljava/lang/StringBuilder; > 68,71 @199 exception:72
in method:advanceToIntersection, at line:165, inst:75 = invokevirtual < Application, Ljava/lang/StringBuilder, toString()Ljava/lang/String; > 73 @202 exception:74
in method:advanceToIntersection, at line:165, inst:invokeinterface < Application, Lorg/slf4j/Logger, debug(Ljava/lang/String;)V > 63,75 @205 exception:76
in method:buildDocKey, at line:174, inst:3 = getstatic < Application, Lorg/apache/accumulo/core/iterators/user/IndexedDocIterator, log, <Application,Lorg/slf4j/Logger> >
in method:buildDocKey, at line:174, inst:5 = invokeinterface < Application, Lorg/slf4j/Logger, isTraceEnabled()Z > 3 @3 exception:4
in method:buildDocKey, at line:174, inst:conditional branch(eq, to iindex=20) 5,6
in method:buildDocKey, at line:174, inst:7 = getstatic < Application, Lorg/apache/accumulo/core/iterators/user/IndexedDocIterator, log, <Application,Lorg/slf4j/Logger> >
in method:buildDocKey, at line:174, inst:8 = new <Application,Ljava/lang/StringBuilder>@14
in method:buildDocKey, at line:174, inst:invokespecial < Application, Ljava/lang/StringBuilder, <init>()V > 8 @18 exception:9
in method:buildDocKey, at line:174, inst:12 = invokevirtual < Application, Ljava/lang/StringBuilder, append(Ljava/lang/String;)Ljava/lang/StringBuilder; > 8,10 @23 exception:11
in method:buildDocKey, at line:175, inst:13 = getfield < Application, Lorg/apache/accumulo/core/iterators/user/IndexedDocIterator, currentPartition, <Application,Lorg/apache/hadoop/io/Text> > 1
in method:buildDocKey, at line:175, inst:15 = invokevirtual < Application, Ljava/lang/StringBuilder, append(Ljava/lang/Object;)Ljava/lang/StringBuilder; > 12,13 @30 exception:14
in method:buildDocKey, at line:175, inst:18 = invokevirtual < Application, Ljava/lang/StringBuilder, append(Ljava/lang/String;)Ljava/lang/StringBuilder; > 15,16 @35 exception:17
in method:buildDocKey, at line:175, inst:19 = getfield < Application, Lorg/apache/accumulo/core/iterators/user/IndexedDocIterator, currentDocID, <Application,Lorg/apache/hadoop/io/Text> > 1
in method:buildDocKey, at line:175, inst:21 = invokevirtual < Application, Ljava/lang/StringBuilder, append(Ljava/lang/Object;)Ljava/lang/StringBuilder; > 18,19 @42 exception:20
in method:buildDocKey, at line:175, inst:23 = invokevirtual < Application, Ljava/lang/StringBuilder, toString()Ljava/lang/String; > 21 @45 exception:22
in method:buildDocKey, at line:175, inst:invokeinterface < Application, Lorg/slf4j/Logger, trace(Ljava/lang/String;)V > 7,23 @48 exception:24
in method:buildDocKey, at line:175, inst:25 = getfield < Application, Lorg/apache/accumulo/core/iterators/user/IndexedDocIterator, currentDocID, <Application,Lorg/apache/hadoop/io/Text> > 1
in method:buildDocKey, at line:175, inst:28 = invokevirtual < Application, Lorg/apache/hadoop/io/Text, find(Ljava/lang/String;)I > 25,26 @59 exception:27
in method:buildDocKey, at line:175, inst:conditional branch(ge, to iindex=33) 28,6
in method:buildDocKey, at line:175, inst:29 = new <Application,Lorg/apache/hadoop/io/Text>@77
in method:buildDocKey, at line:175, inst:30 = getfield < Application, Lorg/apache/accumulo/core/iterators/user/IndexedDocIterator, docColf, <Application,Lorg/apache/hadoop/io/Text> > 1
in method:buildDocKey, at line:175, inst:invokespecial < Application, Lorg/apache/hadoop/io/Text, <init>(Lorg/apache/hadoop/io/Text;)V > 29,30 @85 exception:31
in method:buildDocKey, at line:175, inst:invokevirtual < Application, Lorg/apache/hadoop/io/Text, append([BII)V > 29,32,6,33 @95 exception:34
in method:buildDocKey, at line:175, inst:35 = getfield < Application, Lorg/apache/accumulo/core/iterators/user/IndexedDocIterator, currentDocID, <Application,Lorg/apache/hadoop/io/Text> > 1
in method:buildDocKey, at line:175, inst:37 = invokevirtual < Application, Lorg/apache/hadoop/io/Text, getBytes()[B > 35 @103 exception:36
in method:buildDocKey, at line:175, inst:invokevirtual < Application, Lorg/apache/hadoop/io/Text, append([BII)V > 29,37,6,28 @108 exception:38
in method:buildDocKey, at line:175, inst:39 = new <Application,Lorg/apache/accumulo/core/data/ArrayByteSequence>@112
in method:buildDocKey, at line:176, inst:41 = invokevirtual < Application, Lorg/apache/hadoop/io/Text, getBytes()[B > 29 @117 exception:40
in method:buildDocKey, at line:176, inst:43 = invokevirtual < Application, Lorg/apache/hadoop/io/Text, getLength()I > 29 @122 exception:42
in method:buildDocKey, at line:176, inst:invokespecial < Application, Lorg/apache/accumulo/core/data/ArrayByteSequence, <init>([BII)V > 39,41,6,43 @125 exception:44
in method:buildDocKey, at line:176, inst:46 = invokestatic < Application, Ljava/util/Collections, singleton(Ljava/lang/Object;)Ljava/util/Set; > 39 @128 exception:45
in method:buildDocKey, at line:176, inst:putfield 1.< Application, Lorg/apache/accumulo/core/iterators/user/IndexedDocIterator, docColfSet, <Application,Ljava/util/Set> > = 46
in method:buildDocKey, at line:176, inst:47 = getstatic < Application, Lorg/apache/accumulo/core/iterators/user/IndexedDocIterator, log, <Application,Lorg/slf4j/Logger> >
in method:buildDocKey, at line:177, inst:49 = invokeinterface < Application, Lorg/slf4j/Logger, isTraceEnabled()Z > 47 @137 exception:48
in method:buildDocKey, at line:177, inst:conditional branch(eq, to iindex=80) 49,6
in method:buildDocKey, at line:177, inst:50 = getstatic < Application, Lorg/apache/accumulo/core/iterators/user/IndexedDocIterator, log, <Application,Lorg/slf4j/Logger> >
in method:buildDocKey, at line:178, inst:51 = new <Application,Ljava/lang/StringBuilder>@148
in method:buildDocKey, at line:178, inst:invokespecial < Application, Ljava/lang/StringBuilder, <init>()V > 51 @152 exception:52
in method:buildDocKey, at line:178, inst:54 = invokevirtual < Application, Ljava/lang/StringBuilder, append(I)Ljava/lang/StringBuilder; > 51,28 @156 exception:53
in method:buildDocKey, at line:178, inst:56 = invokevirtual < Application, Ljava/lang/StringBuilder, append(Ljava/lang/String;)Ljava/lang/StringBuilder; > 54,16 @161 exception:55
in method:buildDocKey, at line:178, inst:57 = getfield < Application, Lorg/apache/accumulo/core/iterators/user/IndexedDocIterator, currentDocID, <Application,Lorg/apache/hadoop/io/Text> > 1
in method:buildDocKey, at line:178, inst:59 = invokevirtual < Application, Lorg/apache/hadoop/io/Text, getLength()I > 57 @168 exception:58
in method:buildDocKey, at line:179, inst:61 = invokevirtual < Application, Ljava/lang/StringBuilder, append(I)Ljava/lang/StringBuilder; > 56,59 @171 exception:60
in method:buildDocKey, at line:179, inst:63 = invokevirtual < Application, Ljava/lang/StringBuilder, toString()Ljava/lang/String; > 61 @174 exception:62
in method:buildDocKey, at line:179, inst:invokeinterface < Application, Lorg/slf4j/Logger, trace(Ljava/lang/String;)V > 50,63 @177 exception:64
in method:buildDocKey, at line:179, inst:65 = new <Application,Lorg/apache/hadoop/io/Text>@182
in method:buildDocKey, at line:179, inst:invokespecial < Application, Lorg/apache/hadoop/io/Text, <init>()V > 65 @186 exception:66
in method:buildDocKey, at line:179, inst:67 = getfield < Application, Lorg/apache/accumulo/core/iterators/user/IndexedDocIterator, currentDocID, <Application,Lorg/apache/hadoop/io/Text> > 1
in method:buildDocKey, at line:179, inst:69 = invokevirtual < Application, Lorg/apache/hadoop/io/Text, getBytes()[B > 67 @195 exception:68
in method:buildDocKey, at line:180, inst:70 = binaryop(add) 28 , 33
in method:buildDocKey, at line:180, inst:71 = getfield < Application, Lorg/apache/accumulo/core/iterators/user/IndexedDocIterator, currentDocID, <Application,Lorg/apache/hadoop/io/Text> > 1
in method:buildDocKey, at line:180, inst:73 = invokevirtual < Application, Lorg/apache/hadoop/io/Text, getLength()I > 71 @205 exception:72
in method:buildDocKey, at line:180, inst:74 = binaryop(sub) 73 , 28
in method:buildDocKey, at line:180, inst:75 = binaryop(sub) 74 , 33
in method:buildDocKey, at line:181, inst:invokevirtual < Application, Lorg/apache/hadoop/io/Text, set([BII)V > 65,69,70,75 @212 exception:76
in method:buildDocKey, at line:181, inst:77 = new <Application,Lorg/apache/accumulo/core/data/Key>@215
in method:buildDocKey, at line:181, inst:78 = getfield < Application, Lorg/apache/accumulo/core/iterators/user/IndexedDocIterator, currentPartition, <Application,Lorg/apache/hadoop/io/Text> > 1
in method:buildDocKey, at line:181, inst:invokespecial < Application, Lorg/apache/accumulo/core/data/Key, <init>(Lorg/apache/hadoop/io/Text;Lorg/apache/hadoop/io/Text;Lorg/apache/hadoop/io/Text;)V > 77,78,29,65 @225 exception:79
in method:buildDocKey, at line:181, inst:80 = getstatic < Application, Lorg/apache/accumulo/core/iterators/user/IndexedDocIterator, log, <Application,Lorg/slf4j/Logger> >
in method:buildDocKey, at line:181, inst:82 = invokeinterface < Application, Lorg/slf4j/Logger, isTraceEnabled()Z > 80 @233 exception:81
in method:buildDocKey, at line:181, inst:conditional branch(eq, to iindex=122) 82,6
in method:buildDocKey, at line:182, inst:83 = getstatic < Application, Lorg/apache/accumulo/core/iterators/user/IndexedDocIterator, log, <Application,Lorg/slf4j/Logger> >
in method:buildDocKey, at line:182, inst:84 = new <Application,Ljava/lang/StringBuilder>@244
in method:buildDocKey, at line:182, inst:invokespecial < Application, Ljava/lang/StringBuilder, <init>()V > 84 @248 exception:85
in method:buildDocKey, at line:182, inst:88 = invokevirtual < Application, Ljava/lang/StringBuilder, append(Ljava/lang/String;)Ljava/lang/StringBuilder; > 84,86 @253 exception:87
in method:buildDocKey, at line:182, inst:90 = invokevirtual < Application, Lorg/apache/accumulo/core/data/Key, toString()Ljava/lang/String; > 77 @258 exception:89
in method:buildDocKey, at line:182, inst:92 = invokevirtual < Application, Ljava/lang/StringBuilder, append(Ljava/lang/String;)Ljava/lang/StringBuilder; > 88,90 @261 exception:91
in method:buildDocKey, at line:182, inst:94 = invokevirtual < Application, Ljava/lang/StringBuilder, toString()Ljava/lang/String; > 92 @264 exception:93
in method:buildDocKey, at line:182, inst:invokeinterface < Application, Lorg/slf4j/Logger, trace(Ljava/lang/String;)V > 83,94 @267 exception:95
in method:buildDocKey, at line:182, inst:return 77
in method:toString, at line:931, inst:4 = invokespecial < Application, Lorg/apache/accumulo/core/data/Key, rowColumnStringBuilder()Ljava/lang/StringBuilder; > 1 @1 exception:3
in method:toString, at line:932, inst:7 = invokevirtual < Application, Ljava/lang/StringBuilder, append(Ljava/lang/String;)Ljava/lang/StringBuilder; > 4,5 @8 exception:6
in method:toString, at line:932, inst:10 = invokestatic < Application, Ljava/lang/Long, toString(J)Ljava/lang/String; > 8 @17 exception:9
in method:toString, at line:932, inst:12 = invokevirtual < Application, Ljava/lang/StringBuilder, append(Ljava/lang/String;)Ljava/lang/StringBuilder; > 4,10 @20 exception:11
in method:toString, at line:933, inst:14 = invokevirtual < Application, Ljava/lang/StringBuilder, append(Ljava/lang/String;)Ljava/lang/StringBuilder; > 4,5 @27 exception:13
in method:toString, at line:933, inst:17 = invokevirtual < Application, Ljava/lang/StringBuilder, append(Z)Ljava/lang/StringBuilder; > 4,15 @36 exception:16
in method:toString, at line:933, inst:19 = invokevirtual < Application, Ljava/lang/StringBuilder, toString()Ljava/lang/String; > 4 @41 exception:18
in method:toString, at line:934, inst:return 19
in method:rowColumnStringBuilder, at line:913, inst:5 = invokespecial < Application, Lorg/apache/accumulo/core/data/Key, rowColumnStringBuilder(I)Ljava/lang/StringBuilder; > 1,3 @3 exception:4
in method:rowColumnStringBuilder, at line:913, inst:return 5
in method:rowColumnStringBuilder, at line:917, inst:4 = new <Application,Ljava/lang/StringBuilder>@0
in method:rowColumnStringBuilder, at line:917, inst:invokespecial < Application, Ljava/lang/StringBuilder, <init>()V > 4 @4 exception:5
in method:rowColumnStringBuilder, at line:918, inst:9 = arraylength 8
in method:rowColumnStringBuilder, at line:918, inst:11 = invokestatic < Application, Lorg/apache/accumulo/core/data/Key, appendPrintableString([BIIILjava/lang/StringBuilder;)Ljava/lang/StringBuilder; > 6,7,9,2,4 @20 exception:10
in method:rowColumnStringBuilder, at line:918, inst:14 = invokevirtual < Application, Ljava/lang/StringBuilder, append(Ljava/lang/String;)Ljava/lang/StringBuilder; > 4,12 @27 exception:13
in method:rowColumnStringBuilder, at line:918, inst:17 = arraylength 16
in method:rowColumnStringBuilder, at line:919, inst:19 = invokestatic < Application, Lorg/apache/accumulo/core/data/Key, appendPrintableString([BIIILjava/lang/StringBuilder;)Ljava/lang/StringBuilder; > 15,7,17,2,4 @43 exception:18
in method:rowColumnStringBuilder, at line:919, inst:22 = invokevirtual < Application, Ljava/lang/StringBuilder, append(Ljava/lang/String;)Ljava/lang/StringBuilder; > 4,20 @50 exception:21
in method:rowColumnStringBuilder, at line:920, inst:25 = arraylength 24
in method:rowColumnStringBuilder, at line:920, inst:27 = invokestatic < Application, Lorg/apache/accumulo/core/data/Key, appendPrintableString([BIIILjava/lang/StringBuilder;)Ljava/lang/StringBuilder; > 23,7,25,2,4 @66 exception:26
in method:rowColumnStringBuilder, at line:920, inst:30 = invokevirtual < Application, Ljava/lang/StringBuilder, append(Ljava/lang/String;)Ljava/lang/StringBuilder; > 4,28 @73 exception:29
in method:rowColumnStringBuilder, at line:921, inst:33 = arraylength 32
in method:rowColumnStringBuilder, at line:922, inst:35 = invokestatic < Application, Lorg/apache/accumulo/core/data/Key, appendPrintableString([BIIILjava/lang/StringBuilder;)Ljava/lang/StringBuilder; > 31,7,33,2,4 @89 exception:34
in method:rowColumnStringBuilder, at line:922, inst:38 = invokevirtual < Application, Ljava/lang/StringBuilder, append(Ljava/lang/String;)Ljava/lang/StringBuilder; > 4,36 @96 exception:37
in method:rowColumnStringBuilder, at line:922, inst:return 4
in method:toString, at line:257, inst:3 = new <Application,Ljava/lang/String>@0
in method:toString, at line:257, inst:5 = invokevirtual < Application, Lorg/apache/accumulo/core/data/Value, get()[B > 1 @5 exception:4
in method:toString, at line:257, inst:6 = getstatic < Application, Ljava/nio/charset/StandardCharsets, UTF_8, <Application,Ljava/nio/charset/Charset> >
in method:toString, at line:257, inst:invokespecial < Application, Ljava/lang/String, <init>([BLjava/nio/charset/Charset;)V > 3,5,6 @11 exception:7
in method:toString, at line:257, inst:return 3
in method:equals, at line:768, inst:7 = invokevirtual < Application, Lorg/apache/accumulo/core/data/PartialKey, ordinal()I > 3 @4 exception:6
in method:equals, at line:768, inst:8 = arrayload 5[7]
in method:equals, at line:768, inst:switch 8 [1->5,2->11,3->29,4->54,5->86,6->125]
in method:equals, at line:768, inst:106 = invokestatic < Application, Lorg/apache/accumulo/core/data/Key, isEqual([B[B)Z > 103,104 @56 exception:105
in method:equals, at line:768, inst:return 106
in method:equals, at line:768, inst:97 = invokestatic < Application, Lorg/apache/accumulo/core/data/Key, isEqual([B[B)Z > 94,95 @68 exception:96
in method:equals, at line:768, inst:conditional branch(eq, to iindex=27) 97,24
in method:equals, at line:768, inst:101 = invokestatic < Application, Lorg/apache/accumulo/core/data/Key, isEqual([B[B)Z > 98,99 @82 exception:100
in method:equals, at line:768, inst:conditional branch(eq, to iindex=27) 101,24
in method:equals, at line:768, inst:return 102
in method:equals, at line:768, inst:84 = invokestatic < Application, Lorg/apache/accumulo/core/data/Key, isEqual([B[B)Z > 81,82 @102 exception:83
in method:equals, at line:768, inst:conditional branch(eq, to iindex=52) 84,24
in method:equals, at line:768, inst:88 = invokestatic < Application, Lorg/apache/accumulo/core/data/Key, isEqual([B[B)Z > 85,86 @116 exception:87
in method:equals, at line:768, inst:conditional branch(eq, to iindex=52) 88,24
in method:equals, at line:768, inst:92 = invokestatic < Application, Lorg/apache/accumulo/core/data/Key, isEqual([B[B)Z > 89,90 @130 exception:91
in method:equals, at line:770, inst:conditional branch(eq, to iindex=52) 92,24
in method:equals, at line:770, inst:return 93
in method:equals, at line:770, inst:67 = invokestatic < Application, Lorg/apache/accumulo/core/data/Key, isEqual([B[B)Z > 64,65 @150 exception:66
in method:equals, at line:772, inst:conditional branch(eq, to iindex=84) 67,24
in method:equals, at line:772, inst:71 = invokestatic < Application, Lorg/apache/accumulo/core/data/Key, isEqual([B[B)Z > 68,69 @164 exception:70
in method:equals, at line:772, inst:conditional branch(eq, to iindex=84) 71,24
in method:equals, at line:772, inst:75 = invokestatic < Application, Lorg/apache/accumulo/core/data/Key, isEqual([B[B)Z > 72,73 @178 exception:74
in method:equals, at line:772, inst:conditional branch(eq, to iindex=84) 75,24
in method:equals, at line:772, inst:79 = invokestatic < Application, Lorg/apache/accumulo/core/data/Key, isEqual([B[B)Z > 76,77 @192 exception:78
in method:equals, at line:772, inst:conditional branch(eq, to iindex=84) 79,24
in method:equals, at line:772, inst:return 80
in method:equals, at line:772, inst:47 = invokestatic < Application, Lorg/apache/accumulo/core/data/Key, isEqual([B[B)Z > 44,45 @212 exception:46
in method:equals, at line:772, inst:conditional branch(eq, to iindex=123) 47,24
in method:equals, at line:774, inst:51 = invokestatic < Application, Lorg/apache/accumulo/core/data/Key, isEqual([B[B)Z > 48,49 @226 exception:50
in method:equals, at line:774, inst:conditional branch(eq, to iindex=123) 51,24
in method:equals, at line:774, inst:55 = invokestatic < Application, Lorg/apache/accumulo/core/data/Key, isEqual([B[B)Z > 52,53 @240 exception:54
in method:equals, at line:774, inst:conditional branch(eq, to iindex=123) 55,24
in method:equals, at line:774, inst:59 = invokestatic < Application, Lorg/apache/accumulo/core/data/Key, isEqual([B[B)Z > 56,57 @254 exception:58
in method:equals, at line:774, inst:conditional branch(eq, to iindex=123) 59,24
in method:equals, at line:774, inst:62 = compare 60,61 opcode=cmp
in method:equals, at line:774, inst:conditional branch(ne, to iindex=123) 62,24
in method:equals, at line:774, inst:return 63
in method:equals, at line:774, inst:23 = invokestatic < Application, Lorg/apache/accumulo/core/data/Key, isEqual([B[B)Z > 20,21 @286 exception:22
in method:equals, at line:774, inst:conditional branch(eq, to iindex=167) 23,24
in method:equals, at line:774, inst:28 = invokestatic < Application, Lorg/apache/accumulo/core/data/Key, isEqual([B[B)Z > 25,26 @300 exception:27
in method:equals, at line:774, inst:conditional branch(eq, to iindex=167) 28,24
in method:equals, at line:776, inst:32 = invokestatic < Application, Lorg/apache/accumulo/core/data/Key, isEqual([B[B)Z > 29,30 @314 exception:31
in method:equals, at line:776, inst:conditional branch(eq, to iindex=167) 32,24
in method:equals, at line:776, inst:36 = invokestatic < Application, Lorg/apache/accumulo/core/data/Key, isEqual([B[B)Z > 33,34 @328 exception:35
in method:equals, at line:776, inst:conditional branch(eq, to iindex=167) 36,24
in method:equals, at line:776, inst:39 = compare 37,38 opcode=cmp
in method:equals, at line:776, inst:conditional branch(ne, to iindex=167) 39,24
in method:equals, at line:776, inst:conditional branch(ne, to iindex=167) 40,41
in method:equals, at line:776, inst:return 43
in method:get, at line:165, inst:conditional branch(ne, to iindex=11) 3,4
in method:get, at line:165, inst:conditional branch(ne, to iindex=11) 5,6
in method:get, at line:165, inst:return 7
in method:isEqual, at line:981, inst:conditional branch(ne, to iindex=5) 1,2
in method:isEqual, at line:981, inst:return 13
in method:isEqual, at line:982, inst:4 = arraylength 1
in method:isEqual, at line:986, inst:5 = arraylength 2
in method:isEqual, at line:986, inst:conditional branch(eq, to iindex=14) 4,5
in method:isEqual, at line:986, inst:return 6
in method:isEqual, at line:987, inst:conditional branch(ne, to iindex=19) 4,6
in method:isEqual, at line:989, inst:return 13
in method:isEqual, at line:989, inst:8 = binaryop(add) 4 , 7
in method:isEqual, at line:1002, inst:9 = arrayload 1[8]
in method:isEqual, at line:1004, inst:10 = arrayload 2[8]
in method:isEqual, at line:1004, inst:conditional branch(ne, to iindex=50) 9,10
in method:isEqual, at line:1004, inst:conditional branch(ge, to iindex=49) 15,8
in method:isEqual, at line:1005, inst:11 = arrayload 1[15]
in method:isEqual, at line:1005, inst:12 = arrayload 2[15]
in method:isEqual, at line:1005, inst:conditional branch(eq, to iindex=44) 11,12
in method:isEqual, at line:1006, inst:return 6
in method:isEqual, at line:1006, inst:14 = binaryop(add) 15 , 13
in method:isEqual, at line:1006, inst:return 6
in method:isEqual, at line:1007, inst:return 13
